gputils_api/__init__.py
gputils_api/gputils_api.py
gputils_api-1.7.2.dist-info/METADATA
gputils_api-1.7.2.dist-info/WHEEL
gputils_api-1.7.2.dist-info/top_level.txt
gputils_api-1.7.2.dist-info/RECORD
