Metadata-Version: 2.1
Name: gputils-api
Version: 1.7.2
Summary: Python API for GPUtils
Home-page: https://github.com/GPUEngineering/GPUtils
Author: ['Pantelis Sopasakis', 'Ruairi Moran']
Author-email: xzu.trustful191@passinbox.com
License: GNU General Public License v3 (GPLv3)
Keywords: api,GPU
Platform: UNKNOWN
Classifier: Development Status :: 2 - Pre-Alpha
Classifier: License :: OSI Approved :: GNU General Public License v3 (GPLv3)
Classifier: Programming Language :: Python
Classifier: Environment :: GPU :: NVIDIA CUDA
Classifier: Intended Audience :: Developers
Classifier: Topic :: Software Development :: Libraries
Requires-Dist: numpy
Requires-Dist: setuptools
